{
   "agent": "websock server",
   "behavior": "OK",
   "behaviorClose": "OK",
   "case": 72,
   "closedByMe": false,
   "createStats": true,
   "createWirelog": true,
   "description": "Send invalid UTF-8 text message unfragmented.<br><br>MESSAGE:<br>cebae1bdb9cf83cebcceb5eda080656469746564",
   "droppedByMe": false,
   "duration": 0,
   "expectation": "The connection is failed immediately, since the payload is not valid UTF-8.",
   "expected": {
      "OK": []
   },
   "expectedClose": {
      "closeCode": [
         1007
      ],
      "closedByMe": false,
      "closedByWrongEndpointIsFatal": true,
      "requireClean": false
   },
   "failedByMe": false,
   "httpRequest": "GET /ws HTTP/1.1\r\nUser-Agent: AutobahnTestSuite/25.10.1-0.10.9\r\nHost: 127.0.0.1:8888\r\nUpgrade: WebSocket\r\nConnection: Upgrade\r\nPragma: no-cache\r\nCache-Control: no-cache\r\nSec-WebSocket-Key: 1ug72yrEq9pN+awS5ICHSw==\r\nSec-WebSocket-Version: 13\r\n\r\n",
   "httpResponse": "HTTP/1.1 101 Switching Protocols\r\nDate: Fri, 05 Dec 2025 02:31:12 GMT\r\nConnection: Upgrade\r\nUpgrade: websocket\r\nSec-Websocket-Accept: 35Hk9n3d6a1Epvo1xaOlplbjPQY=\r\n\r\n",
   "id": "6.3.1",
   "isServer": false,
   "localCloseCode": null,
   "localCloseReason": null,
   "received": [],
   "remoteCloseCode": null,
   "remoteCloseReason": null,
   "reportCompressionRatio": false,
   "reportTime": false,
   "result": "Actual events match at least one expected.",
   "resultClose": "Connection was properly closed",
   "rxFrameStats": {},
   "rxOctetStats": {
      "166": 1
   },
   "started": "2025-12-05T02:31:12.784Z",
   "trafficStats": null,
   "txFrameStats": {
      "1": 1
   },
   "txOctetStats": {
      "26": 1,
      "244": 1
   },
   "wasClean": false,
   "wasCloseHandshakeTimeout": false,
   "wasNotCleanReason": "peer dropped the TCP connection without previous WebSocket closing handshake",
   "wasOpenHandshakeTimeout": false,
   "wasServerConnectionDropTimeout": false,
   "wirelog": [
      [
         "TO",
         [
            244,
            "474554202f777320485454502f312e310d0a557365722d4167656e743a204175746f6261686e5465737453756974652f32352e31302e312d302e31302e390d0a ..."
         ],
         false
      ],
      [
         "RO",
         [
            166,
            "485454502f312e312031303120537769746368696e672050726f746f636f6c730d0a446174653a204672692c2030352044656320323032352030323a33313a31 ..."
         ]
      ],
      [
         "TF",
         [
            20,
            "\u03ba\u1f79\u03c3\u03bc\u03b5\ud800edited"
         ],
         1,
         true,
         0,
         "bac628f8",
         null,
         null,
         false
      ],
      [
         "TO",
         [
            26,
            "8194bac628f8747cc9450309ab3606089d151a464d9cd3b24d9c"
         ],
         false
      ],
      [
         "KL",
         1
      ]
   ]
}