{
   "agent": "websock secure server",
   "behavior": "OK",
   "behaviorClose": "OK",
   "case": 61,
   "closedByMe": false,
   "createStats": true,
   "createWirelog": true,
   "description": "Repeated 2x: Continuation Frame with FIN = true (where there is nothing to continue), then text Message fragmented into 2 fragments.",
   "droppedByMe": false,
   "duration": 1,
   "expectation": "The connection is failed immediately, since there is no message to continue.",
   "expected": {
      "OK": []
   },
   "expectedClose": {
      "closeCode": [
         1002
      ],
      "closedByMe": false,
      "requireClean": false
   },
   "failedByMe": false,
   "httpRequest": "GET /wss HTTP/1.1\r\nUser-Agent: AutobahnTestSuite/25.10.1-0.10.9\r\nHost: 127.0.0.1:8889\r\nUpgrade: WebSocket\r\nConnection: Upgrade\r\nPragma: no-cache\r\nCache-Control: no-cache\r\nSec-WebSocket-Key: sEUSWZd9hm1mJlosW/Q5BA==\r\nSec-WebSocket-Version: 13\r\n\r\n",
   "httpResponse": "HTTP/1.1 101 Switching Protocols\r\nDate: Sat, 15 Nov 2025 09:27:43 GMT\r\nConnection: Upgrade\r\nUpgrade: websocket\r\nSec-Websocket-Accept: YcKV0evtIVsWRlb4tFQpfv2dElc=\r\n\r\n",
   "id": "5.17",
   "isServer": false,
   "localCloseCode": null,
   "localCloseReason": null,
   "received": [],
   "remoteCloseCode": null,
   "remoteCloseReason": null,
   "reportCompressionRatio": false,
   "reportTime": false,
   "result": "Actual events match at least one expected.",
   "resultClose": "Connection was properly closed",
   "rxFrameStats": {},
   "rxOctetStats": {
      "166": 1
   },
   "started": "2025-11-15T09:27:43.262Z",
   "trafficStats": null,
   "txFrameStats": {
      "0": 4,
      "1": 2
   },
   "txOctetStats": {
      "15": 6,
      "245": 1
   },
   "wasClean": false,
   "wasCloseHandshakeTimeout": false,
   "wasNotCleanReason": "peer dropped the TCP connection without previous WebSocket closing handshake",
   "wasOpenHandshakeTimeout": false,
   "wasServerConnectionDropTimeout": false,
   "wirelog": [
      [
         "TO",
         [
            245,
            "474554202f77737320485454502f312e310d0a557365722d4167656e743a204175746f6261686e5465737453756974652f32352e31302e312d302e31302e390d ..."
         ],
         false
      ],
      [
         "RO",
         [
            166,
            "485454502f312e312031303120537769746368696e672050726f746f636f6c730d0a446174653a205361742c203135204e6f7620323032352030393a32373a34 ..."
         ]
      ],
      [
         "TF",
         [
            9,
            "fragment1"
         ],
         0,
         true,
         0,
         "e91be64b",
         null,
         null,
         false
      ],
      [
         "TO",
         [
            15,
            "8089e91be64b8f69872c847e883fd8"
         ],
         false
      ],
      [
         "TF",
         [
            9,
            "fragment2"
         ],
         1,
         false,
         0,
         "29e50a20",
         null,
         null,
         false
      ],
      [
         "TO",
         [
            15,
            "018929e50a204f976b47448064541b"
         ],
         false
      ],
      [
         "TF",
         [
            9,
            "fragment3"
         ],
         0,
         true,
         0,
         "8661558b",
         null,
         null,
         false
      ],
      [
         "TO",
         [
            15,
            "80898661558be01334eceb043bffb5"
         ],
         false
      ],
      [
         "TF",
         [
            9,
            "fragment1"
         ],
         0,
         true,
         0,
         "a920a788",
         null,
         null,
         false
      ],
      [
         "TO",
         [
            15,
            "8089a920a788cf52c6efc445c9fc98"
         ],
         false
      ],
      [
         "TF",
         [
            9,
            "fragment2"
         ],
         1,
         false,
         0,
         "57716b29",
         null,
         null,
         false
      ],
      [
         "TO",
         [
            15,
            "018957716b2931030a4e3a14055d65"
         ],
         false
      ],
      [
         "TF",
         [
            9,
            "fragment3"
         ],
         0,
         true,
         0,
         "72199762",
         null,
         null,
         false
      ],
      [
         "TO",
         [
            15,
            "808972199762146bf6051f7cf91641"
         ],
         false
      ],
      [
         "KL",
         1
      ]
   ]
}