{
   "agent": "websock secure server",
   "behavior": "OK",
   "behaviorClose": "UNCLEAN",
   "case": 26,
   "closedByMe": true,
   "createStats": true,
   "createWirelog": true,
   "description": "Send 10 Pings with payload.",
   "droppedByMe": false,
   "duration": 4,
   "expectation": "Pongs for our Pings with all the payloads. Note: This is not required by the Spec .. but we check for this behaviour anyway. Clean close with normal code.",
   "expected": {
      "OK": [
         [
            "pong",
            "payload-0"
         ],
         [
            "pong",
            "payload-1"
         ],
         [
            "pong",
            "payload-2"
         ],
         [
            "pong",
            "payload-3"
         ],
         [
            "pong",
            "payload-4"
         ],
         [
            "pong",
            "payload-5"
         ],
         [
            "pong",
            "payload-6"
         ],
         [
            "pong",
            "payload-7"
         ],
         [
            "pong",
            "payload-8"
         ],
         [
            "pong",
            "payload-9"
         ]
      ]
   },
   "expectedClose": {
      "closeCode": [
         1000
      ],
      "closedByMe": true,
      "requireClean": true
   },
   "failedByMe": false,
   "httpRequest": "GET /wss HTTP/1.1\r\nUser-Agent: AutobahnTestSuite/25.10.1-0.10.9\r\nHost: 127.0.0.1:8889\r\nUpgrade: WebSocket\r\nConnection: Upgrade\r\nPragma: no-cache\r\nCache-Control: no-cache\r\nSec-WebSocket-Key: 0R2kNuGTu/XnGsiW5qLy1Q==\r\nSec-WebSocket-Version: 13\r\n\r\n",
   "httpResponse": "HTTP/1.1 101 Switching Protocols\r\nDate: Tue, 31 Mar 2026 17:40:50 GMT\r\nConnection: Upgrade\r\nUpgrade: websocket\r\nSec-Websocket-Accept: ik8esXTFHih00eITd2Gf7jNdFx0=\r\n\r\n",
   "id": "2.10",
   "isServer": false,
   "localCloseCode": 1000,
   "localCloseReason": null,
   "received": [
      [
         "pong",
         "payload-0"
      ],
      [
         "pong",
         "payload-1"
      ],
      [
         "pong",
         "payload-2"
      ],
      [
         "pong",
         "payload-3"
      ],
      [
         "pong",
         "payload-4"
      ],
      [
         "pong",
         "payload-5"
      ],
      [
         "pong",
         "payload-6"
      ],
      [
         "pong",
         "payload-7"
      ],
      [
         "pong",
         "payload-8"
      ],
      [
         "pong",
         "payload-9"
      ]
   ],
   "remoteCloseCode": null,
   "remoteCloseReason": null,
   "reportCompressionRatio": false,
   "reportTime": false,
   "result": "Actual events match at least one expected.",
   "resultClose": "The spec requires the connection to be failed cleanly here",
   "rxFrameStats": {
      "10": 10
   },
   "rxOctetStats": {
      "11": 10,
      "166": 1
   },
   "started": "2026-03-31T17:40:50.485Z",
   "trafficStats": null,
   "txFrameStats": {
      "8": 1,
      "9": 10
   },
   "txOctetStats": {
      "8": 1,
      "15": 10,
      "245": 1
   },
   "wasClean": false,
   "wasCloseHandshakeTimeout": false,
   "wasNotCleanReason": "peer dropped the TCP connection without previous WebSocket closing handshake",
   "wasOpenHandshakeTimeout": false,
   "wasServerConnectionDropTimeout": false,
   "wirelog": [
      [
         "TO",
         [
            245,
            "474554202f77737320485454502f312e310d0a557365722d4167656e743a204175746f6261686e5465737453756974652f32352e31302e312d302e31302e390d ..."
         ],
         false
      ],
      [
         "RO",
         [
            166,
            "485454502f312e312031303120537769746368696e672050726f746f636f6c730d0a446174653a205475652c203331204d617220323032362031373a34303a35 ..."
         ]
      ],
      [
         "TF",
         [
            9,
            "payload-0"
         ],
         9,
         true,
         0,
         "fe6ec13e",
         null,
         null,
         false
      ],
      [
         "TO",
         [
            15,
            "8989fe6ec13e8e0fb852910fa513ce"
         ],
         false
      ],
      [
         "TF",
         [
            9,
            "payload-1"
         ],
         9,
         true,
         0,
         "3ee117e5",
         null,
         null,
         false
      ],
      [
         "TO",
         [
            15,
            "89893ee117e54e806e89518073c80f"
         ],
         false
      ],
      [
         "TF",
         [
            9,
            "payload-2"
         ],
         9,
         true,
         0,
         "7d063cc3",
         null,
         null,
         false
      ],
      [
         "TO",
         [
            15,
            "89897d063cc30d6745af126758ee4f"
         ],
         false
      ],
      [
         "TF",
         [
            9,
            "payload-3"
         ],
         9,
         true,
         0,
         "68501911",
         null,
         null,
         false
      ],
      [
         "TO",
         [
            15,
            "8989685019111831607d07317d3c5b"
         ],
         false
      ],
      [
         "TF",
         [
            9,
            "payload-4"
         ],
         9,
         true,
         0,
         "dcb24fd7",
         null,
         null,
         false
      ],
      [
         "TO",
         [
            15,
            "8989dcb24fd7acd336bbb3d32bfae8"
         ],
         false
      ],
      [
         "TF",
         [
            9,
            "payload-5"
         ],
         9,
         true,
         0,
         "5d1ee19f",
         null,
         null,
         false
      ],
      [
         "TO",
         [
            15,
            "89895d1ee19f2d7f98f3327f85b268"
         ],
         false
      ],
      [
         "TF",
         [
            9,
            "payload-6"
         ],
         9,
         true,
         0,
         "e116ed6e",
         null,
         null,
         false
      ],
      [
         "TO",
         [
            15,
            "8989e116ed6e917794028e778943d7"
         ],
         false
      ],
      [
         "TF",
         [
            9,
            "payload-7"
         ],
         9,
         true,
         0,
         "34b51b67",
         null,
         null,
         false
      ],
      [
         "TO",
         [
            15,
            "898934b51b6744d4620b5bd47f4a03"
         ],
         false
      ],
      [
         "TF",
         [
            9,
            "payload-8"
         ],
         9,
         true,
         0,
         "efca0387",
         null,
         null,
         false
      ],
      [
         "TO",
         [
            15,
            "8989efca03879fab7aeb80ab67aad7"
         ],
         false
      ],
      [
         "TF",
         [
            9,
            "payload-9"
         ],
         9,
         true,
         0,
         "9396ce81",
         null,
         null,
         false
      ],
      [
         "TO",
         [
            15,
            "89899396ce81e3f7b7edfcf7aaacaa"
         ],
         false
      ],
      [
         "TI",
         3
      ],
      [
         "RO",
         [
            11,
            "8a097061796c6f61642d30"
         ]
      ],
      [
         "RF",
         [
            9,
            "payload-0"
         ],
         10,
         true,
         0,
         false,
         null
      ],
      [
         "RO",
         [
            11,
            "8a097061796c6f61642d31"
         ]
      ],
      [
         "RF",
         [
            9,
            "payload-1"
         ],
         10,
         true,
         0,
         false,
         null
      ],
      [
         "RO",
         [
            11,
            "8a097061796c6f61642d32"
         ]
      ],
      [
         "RF",
         [
            9,
            "payload-2"
         ],
         10,
         true,
         0,
         false,
         null
      ],
      [
         "RO",
         [
            11,
            "8a097061796c6f61642d33"
         ]
      ],
      [
         "RF",
         [
            9,
            "payload-3"
         ],
         10,
         true,
         0,
         false,
         null
      ],
      [
         "RO",
         [
            11,
            "8a097061796c6f61642d34"
         ]
      ],
      [
         "RF",
         [
            9,
            "payload-4"
         ],
         10,
         true,
         0,
         false,
         null
      ],
      [
         "RO",
         [
            11,
            "8a097061796c6f61642d35"
         ]
      ],
      [
         "RF",
         [
            9,
            "payload-5"
         ],
         10,
         true,
         0,
         false,
         null
      ],
      [
         "RO",
         [
            11,
            "8a097061796c6f61642d36"
         ]
      ],
      [
         "RF",
         [
            9,
            "payload-6"
         ],
         10,
         true,
         0,
         false,
         null
      ],
      [
         "RO",
         [
            11,
            "8a097061796c6f61642d37"
         ]
      ],
      [
         "RF",
         [
            9,
            "payload-7"
         ],
         10,
         true,
         0,
         false,
         null
      ],
      [
         "RO",
         [
            11,
            "8a097061796c6f61642d38"
         ]
      ],
      [
         "RF",
         [
            9,
            "payload-8"
         ],
         10,
         true,
         0,
         false,
         null
      ],
      [
         "RO",
         [
            11,
            "8a097061796c6f61642d39"
         ]
      ],
      [
         "RF",
         [
            9,
            "payload-9"
         ],
         10,
         true,
         0,
         false,
         null
      ],
      [
         "TF",
         [
            2,
            "0x03e8"
         ],
         8,
         true,
         0,
         "b4fb7bcc",
         null,
         null,
         false
      ],
      [
         "TO",
         [
            8,
            "8882b4fb7bccb713"
         ],
         false
      ]
   ]
}