{
   "agent": "websock secure server",
   "behavior": "OK",
   "behaviorClose": "OK",
   "case": 71,
   "closedByMe": true,
   "createStats": true,
   "createWirelog": true,
   "description": "Send a valid UTF-8 text message in fragments of 1 octet, resulting in frames ending on positions which are not code point ends.<br><br>MESSAGE:<br>\u03ba\u1f79\u03c3\u03bc\u03b5<br>cebae1bdb9cf83cebcceb5",
   "droppedByMe": false,
   "duration": 11,
   "expectation": "The message is echo'ed back to us.",
   "expected": {
      "OK": [
         [
            "message",
            "\u03ba\u1f79\u03c3\u03bc\u03b5",
            false
         ]
      ]
   },
   "expectedClose": {
      "closeCode": [
         1000
      ],
      "closedByMe": true,
      "requireClean": true
   },
   "failedByMe": false,
   "httpRequest": "GET /wss HTTP/1.1\r\nUser-Agent: AutobahnTestSuite/0.8.2-0.10.9\r\nHost: 127.0.0.1:8889\r\nUpgrade: WebSocket\r\nConnection: Upgrade\r\nPragma: no-cache\r\nCache-Control: no-cache\r\nSec-WebSocket-Key: edy0w/BBGir8U6uEt0DW+w==\r\nSec-WebSocket-Version: 13\r\n\r\n",
   "httpResponse": "HTTP/1.1 101 Switching Protocols\r\nDate: Tue, 23 Jan 2024 05:47:40 GMT\r\nUpgrade: websocket\r\nConnection: Upgrade\r\nSec-Websocket-Accept: eC4kxQmhmQ2MuieOdYOfRMEdzCA=\r\n\r\n",
   "id": "6.2.4",
   "isServer": false,
   "localCloseCode": 1000,
   "localCloseReason": null,
   "received": [
      [
         "message",
         "\u03ba\u1f79\u03c3\u03bc\u03b5",
         false
      ]
   ],
   "remoteCloseCode": 1000,
   "remoteCloseReason": null,
   "reportCompressionRatio": false,
   "reportTime": false,
   "result": "Actual events match at least one expected.",
   "resultClose": "Connection was properly closed",
   "rxFrameStats": {
      "1": 1,
      "8": 1
   },
   "rxOctetStats": {
      "4": 1,
      "13": 1,
      "166": 1
   },
   "started": "2024-01-23T05:47:40.336Z",
   "trafficStats": null,
   "txFrameStats": {
      "0": 11,
      "1": 1,
      "8": 1
   },
   "txOctetStats": {
      "6": 1,
      "7": 11,
      "8": 1,
      "243": 1
   },
   "wasClean": true,
   "wasCloseHandshakeTimeout": false,
   "wasNotCleanReason": null,
   "wasOpenHandshakeTimeout": false,
   "wasServerConnectionDropTimeout": false,
   "wirelog": [
      [
         "TO",
         [
            243,
            "474554202f77737320485454502f312e310d0a557365722d4167656e743a204175746f6261686e5465737453756974652f302e382e322d302e31302e390d0a48 ..."
         ],
         false
      ],
      [
         "RO",
         [
            166,
            "485454502f312e312031303120537769746368696e672050726f746f636f6c730d0a446174653a205475652c203233204a616e20323032342030353a34373a34 ..."
         ]
      ],
      [
         "TF",
         [
            1,
            "0xce"
         ],
         1,
         false,
         0,
         "de1340eb",
         null,
         null,
         false
      ],
      [
         "TO",
         [
            7,
            "0181de1340eb10"
         ],
         false
      ],
      [
         "TF",
         [
            1,
            "0xba"
         ],
         0,
         false,
         0,
         "a007d4eb",
         null,
         null,
         false
      ],
      [
         "TO",
         [
            7,
            "0081a007d4eb1a"
         ],
         false
      ],
      [
         "TF",
         [
            1,
            "0xe1"
         ],
         0,
         false,
         0,
         "868fee11",
         null,
         null,
         false
      ],
      [
         "TO",
         [
            7,
            "0081868fee1167"
         ],
         false
      ],
      [
         "TF",
         [
            1,
            "0xbd"
         ],
         0,
         false,
         0,
         "5c50fef6",
         null,
         null,
         false
      ],
      [
         "TO",
         [
            7,
            "00815c50fef6e1"
         ],
         false
      ],
      [
         "TF",
         [
            1,
            "0xb9"
         ],
         0,
         false,
         0,
         "a3c3edc2",
         null,
         null,
         false
      ],
      [
         "TO",
         [
            7,
            "0081a3c3edc21a"
         ],
         false
      ],
      [
         "TF",
         [
            1,
            "0xcf"
         ],
         0,
         false,
         0,
         "aa1a5607",
         null,
         null,
         false
      ],
      [
         "TO",
         [
            7,
            "0081aa1a560765"
         ],
         false
      ],
      [
         "TF",
         [
            1,
            "0x83"
         ],
         0,
         false,
         0,
         "17a8fbcb",
         null,
         null,
         false
      ],
      [
         "TO",
         [
            7,
            "008117a8fbcb94"
         ],
         false
      ],
      [
         "TF",
         [
            1,
            "0xce"
         ],
         0,
         false,
         0,
         "2392ffa9",
         null,
         null,
         false
      ],
      [
         "TO",
         [
            7,
            "00812392ffa9ed"
         ],
         false
      ],
      [
         "TF",
         [
            1,
            "0xbc"
         ],
         0,
         false,
         0,
         "70b85577",
         null,
         null,
         false
      ],
      [
         "TO",
         [
            7,
            "008170b85577cc"
         ],
         false
      ],
      [
         "TF",
         [
            1,
            "0xce"
         ],
         0,
         false,
         0,
         "d4fc2cb5",
         null,
         null,
         false
      ],
      [
         "TO",
         [
            7,
            "0081d4fc2cb51a"
         ],
         false
      ],
      [
         "TF",
         [
            1,
            "0xb5"
         ],
         0,
         false,
         0,
         "f22ba026",
         null,
         null,
         false
      ],
      [
         "TO",
         [
            7,
            "0081f22ba02647"
         ],
         false
      ],
      [
         "TF",
         [
            0,
            ""
         ],
         0,
         true,
         0,
         "4f57a9e3",
         null,
         null,
         false
      ],
      [
         "TO",
         [
            6,
            "80804f57a9e3"
         ],
         false
      ],
      [
         "TI",
         1
      ],
      [
         "RO",
         [
            13,
            "810bcebae1bdb9cf83cebcceb5"
         ]
      ],
      [
         "RF",
         [
            11,
            "\u03ba\u1f79\u03c3\u03bc\u03b5"
         ],
         1,
         true,
         0,
         false,
         null
      ],
      [
         "TF",
         [
            2,
            "0x03e8"
         ],
         8,
         true,
         0,
         "7d5fe408",
         null,
         null,
         false
      ],
      [
         "TO",
         [
            8,
            "88827d5fe4087eb7"
         ],
         false
      ],
      [
         "RO",
         [
            4,
            "880203e8"
         ]
      ],
      [
         "RF",
         [
            2,
            "0x03e8"
         ],
         8,
         true,
         0,
         false,
         null
      ]
   ]
}