{
   "agent": "websock server",
   "behavior": "OK",
   "behaviorClose": "UNCLEAN",
   "case": 301,
   "closedByMe": true,
   "createStats": true,
   "createWirelog": true,
   "description": "Send text message with payload of length 65536 auto-fragmented with <b>autoFragmentSize = 1300</b>.",
   "droppedByMe": false,
   "duration": 4,
   "expectation": "Receive echo'ed text message (with payload as sent and transmitted frame counts as expected). Clean close with normal code.",
   "expected": {
      "OK": [
         [
            "message",
            "**************************************************************** ...",
            false
         ]
      ]
   },
   "expectedClose": {
      "closeCode": [
         1000
      ],
      "closedByMe": true,
      "requireClean": true
   },
   "failedByMe": false,
   "httpRequest": "GET /ws HTTP/1.1\r\nUser-Agent: AutobahnTestSuite/25.10.1-0.10.9\r\nHost: 127.0.0.1:8888\r\nUpgrade: WebSocket\r\nConnection: Upgrade\r\nPragma: no-cache\r\nCache-Control: no-cache\r\nSec-WebSocket-Key: Jhbt2mIhNR5Q23axpaRd8g==\r\nSec-WebSocket-Version: 13\r\n\r\n",
   "httpResponse": "HTTP/1.1 101 Switching Protocols\r\nDate: Sat, 11 Apr 2026 02:37:46 GMT\r\nUpgrade: websocket\r\nConnection: Upgrade\r\nSec-Websocket-Accept: 9xtnWyoMUb2LavvwY6xmSdrZmWQ=\r\n\r\n",
   "id": "10.1.1",
   "isServer": false,
   "localCloseCode": 1000,
   "localCloseReason": null,
   "received": [
      [
         "message",
         "**************************************************************** ...",
         false
      ]
   ],
   "remoteCloseCode": null,
   "remoteCloseReason": null,
   "reportCompressionRatio": false,
   "reportTime": false,
   "result": "Actual events match at least one expected.",
   "resultClose": "The spec requires the connection to be failed cleanly here",
   "rxFrameStats": {
      "1": 1
   },
   "rxOctetStats": {
      "10": 1,
      "166": 1,
      "65536": 1
   },
   "started": "2026-04-11T02:37:46.713Z",
   "trafficStats": null,
   "txFrameStats": {
      "0": 50,
      "1": 1,
      "8": 1
   },
   "txOctetStats": {
      "8": 1,
      "244": 1,
      "544": 1,
      "1308": 50
   },
   "wasClean": false,
   "wasCloseHandshakeTimeout": false,
   "wasNotCleanReason": "peer dropped the TCP connection without previous WebSocket closing handshake",
   "wasOpenHandshakeTimeout": false,
   "wasServerConnectionDropTimeout": false,
   "wirelog": [
      [
         "TO",
         [
            244,
            "474554202f777320485454502f312e310d0a557365722d4167656e743a204175746f6261686e5465737453756974652f32352e31302e312d302e31302e390d0a ..."
         ],
         false
      ],
      [
         "RO",
         [
            166,
            "485454502f312e312031303120537769746368696e672050726f746f636f6c730d0a446174653a205361742c2031312041707220323032362030323a33373a34 ..."
         ]
      ],
      [
         "TF",
         [
            1300,
            "**************************************************************** ..."
         ],
         1,
         false,
         0,
         "02e038b0",
         null,
         null,
         false
      ],
      [
         "TO",
         [
            1308,
            "01fe051402e038b028ca129a28ca129a28ca129a28ca129a28ca129a28ca129a28ca129a28ca129a28ca129a28ca129a28ca129a28ca129a28ca129a28ca129a ..."
         ],
         false
      ],
      [
         "TF",
         [
            1300,
            "**************************************************************** ..."
         ],
         0,
         false,
         0,
         "bdf62fc7",
         null,
         null,
         false
      ],
      [
         "TO",
         [
            1308,
            "00fe0514bdf62fc797dc05ed97dc05ed97dc05ed97dc05ed97dc05ed97dc05ed97dc05ed97dc05ed97dc05ed97dc05ed97dc05ed97dc05ed97dc05ed97dc05ed ..."
         ],
         false
      ],
      [
         "TF",
         [
            1300,
            "**************************************************************** ..."
         ],
         0,
         false,
         0,
         "7765af37",
         null,
         null,
         false
      ],
      [
         "TO",
         [
            1308,
            "00fe05147765af375d4f851d5d4f851d5d4f851d5d4f851d5d4f851d5d4f851d5d4f851d5d4f851d5d4f851d5d4f851d5d4f851d5d4f851d5d4f851d5d4f851d ..."
         ],
         false
      ],
      [
         "TF",
         [
            1300,
            "**************************************************************** ..."
         ],
         0,
         false,
         0,
         "4b0bb351",
         null,
         null,
         false
      ],
      [
         "TO",
         [
            1308,
            "00fe05144b0bb3516121997b6121997b6121997b6121997b6121997b6121997b6121997b6121997b6121997b6121997b6121997b6121997b6121997b6121997b ..."
         ],
         false
      ],
      [
         "TF",
         [
            1300,
            "**************************************************************** ..."
         ],
         0,
         false,
         0,
         "0b40578b",
         null,
         null,
         false
      ],
      [
         "TO",
         [
            1308,
            "00fe05140b40578b216a7da1216a7da1216a7da1216a7da1216a7da1216a7da1216a7da1216a7da1216a7da1216a7da1216a7da1216a7da1216a7da1216a7da1 ..."
         ],
         false
      ],
      [
         "TF",
         [
            1300,
            "**************************************************************** ..."
         ],
         0,
         false,
         0,
         "892863b6",
         null,
         null,
         false
      ],
      [
         "TO",
         [
            1308,
            "00fe0514892863b6a302499ca302499ca302499ca302499ca302499ca302499ca302499ca302499ca302499ca302499ca302499ca302499ca302499ca302499c ..."
         ],
         false
      ],
      [
         "TF",
         [
            1300,
            "**************************************************************** ..."
         ],
         0,
         false,
         0,
         "1d951231",
         null,
         null,
         false
      ],
      [
         "TO",
         [
            1308,
            "00fe05141d95123137bf381b37bf381b37bf381b37bf381b37bf381b37bf381b37bf381b37bf381b37bf381b37bf381b37bf381b37bf381b37bf381b37bf381b ..."
         ],
         false
      ],
      [
         "TF",
         [
            1300,
            "**************************************************************** ..."
         ],
         0,
         false,
         0,
         "704b5f00",
         null,
         null,
         false
      ],
      [
         "TO",
         [
            1308,
            "00fe0514704b5f005a61752a5a61752a5a61752a5a61752a5a61752a5a61752a5a61752a5a61752a5a61752a5a61752a5a61752a5a61752a5a61752a5a61752a ..."
         ],
         false
      ],
      [
         "TF",
         [
            1300,
            "**************************************************************** ..."
         ],
         0,
         false,
         0,
         "abaa70e1",
         null,
         null,
         false
      ],
      [
         "TO",
         [
            1308,
            "00fe0514abaa70e181805acb81805acb81805acb81805acb81805acb81805acb81805acb81805acb81805acb81805acb81805acb81805acb81805acb81805acb ..."
         ],
         false
      ],
      [
         "TF",
         [
            1300,
            "**************************************************************** ..."
         ],
         0,
         false,
         0,
         "76eac9a5",
         null,
         null,
         false
      ],
      [
         "TO",
         [
            1308,
            "00fe051476eac9a55cc0e38f5cc0e38f5cc0e38f5cc0e38f5cc0e38f5cc0e38f5cc0e38f5cc0e38f5cc0e38f5cc0e38f5cc0e38f5cc0e38f5cc0e38f5cc0e38f ..."
         ],
         false
      ],
      [
         "TF",
         [
            1300,
            "**************************************************************** ..."
         ],
         0,
         false,
         0,
         "d36ef0a0",
         null,
         null,
         false
      ],
      [
         "TO",
         [
            1308,
            "00fe0514d36ef0a0f944da8af944da8af944da8af944da8af944da8af944da8af944da8af944da8af944da8af944da8af944da8af944da8af944da8af944da8a ..."
         ],
         false
      ],
      [
         "TF",
         [
            1300,
            "**************************************************************** ..."
         ],
         0,
         false,
         0,
         "c5557e5b",
         null,
         null,
         false
      ],
      [
         "TO",
         [
            1308,
            "00fe0514c5557e5bef7f5471ef7f5471ef7f5471ef7f5471ef7f5471ef7f5471ef7f5471ef7f5471ef7f5471ef7f5471ef7f5471ef7f5471ef7f5471ef7f5471 ..."
         ],
         false
      ],
      [
         "TF",
         [
            1300,
            "**************************************************************** ..."
         ],
         0,
         false,
         0,
         "992e40c9",
         null,
         null,
         false
      ],
      [
         "TO",
         [
            1308,
            "00fe0514992e40c9b3046ae3b3046ae3b3046ae3b3046ae3b3046ae3b3046ae3b3046ae3b3046ae3b3046ae3b3046ae3b3046ae3b3046ae3b3046ae3b3046ae3 ..."
         ],
         false
      ],
      [
         "TF",
         [
            1300,
            "**************************************************************** ..."
         ],
         0,
         false,
         0,
         "5d52a2b9",
         null,
         null,
         false
      ],
      [
         "TO",
         [
            1308,
            "00fe05145d52a2b97778889377788893777888937778889377788893777888937778889377788893777888937778889377788893777888937778889377788893 ..."
         ],
         false
      ],
      [
         "TF",
         [
            1300,
            "**************************************************************** ..."
         ],
         0,
         false,
         0,
         "fa8b3be0",
         null,
         null,
         false
      ],
      [
         "TO",
         [
            1308,
            "00fe0514fa8b3be0d0a111cad0a111cad0a111cad0a111cad0a111cad0a111cad0a111cad0a111cad0a111cad0a111cad0a111cad0a111cad0a111cad0a111ca ..."
         ],
         false
      ],
      [
         "TF",
         [
            1300,
            "**************************************************************** ..."
         ],
         0,
         false,
         0,
         "aaf54898",
         null,
         null,
         false
      ],
      [
         "TO",
         [
            1308,
            "00fe0514aaf5489880df62b280df62b280df62b280df62b280df62b280df62b280df62b280df62b280df62b280df62b280df62b280df62b280df62b280df62b2 ..."
         ],
         false
      ],
      [
         "TF",
         [
            1300,
            "**************************************************************** ..."
         ],
         0,
         false,
         0,
         "0c49b533",
         null,
         null,
         false
      ],
      [
         "TO",
         [
            1308,
            "00fe05140c49b53326639f1926639f1926639f1926639f1926639f1926639f1926639f1926639f1926639f1926639f1926639f1926639f1926639f1926639f19 ..."
         ],
         false
      ],
      [
         "TF",
         [
            1300,
            "**************************************************************** ..."
         ],
         0,
         false,
         0,
         "ae472482",
         null,
         null,
         false
      ],
      [
         "TO",
         [
            1308,
            "00fe0514ae472482846d0ea8846d0ea8846d0ea8846d0ea8846d0ea8846d0ea8846d0ea8846d0ea8846d0ea8846d0ea8846d0ea8846d0ea8846d0ea8846d0ea8 ..."
         ],
         false
      ],
      [
         "TF",
         [
            1300,
            "**************************************************************** ..."
         ],
         0,
         false,
         0,
         "971a5218",
         null,
         null,
         false
      ],
      [
         "TO",
         [
            1308,
            "00fe0514971a5218bd307832bd307832bd307832bd307832bd307832bd307832bd307832bd307832bd307832bd307832bd307832bd307832bd307832bd307832 ..."
         ],
         false
      ],
      [
         "TF",
         [
            1300,
            "**************************************************************** ..."
         ],
         0,
         false,
         0,
         "82da2e3b",
         null,
         null,
         false
      ],
      [
         "TO",
         [
            1308,
            "00fe051482da2e3ba8f00411a8f00411a8f00411a8f00411a8f00411a8f00411a8f00411a8f00411a8f00411a8f00411a8f00411a8f00411a8f00411a8f00411 ..."
         ],
         false
      ],
      [
         "TF",
         [
            1300,
            "**************************************************************** ..."
         ],
         0,
         false,
         0,
         "cc9e41de",
         null,
         null,
         false
      ],
      [
         "TO",
         [
            1308,
            "00fe0514cc9e41dee6b46bf4e6b46bf4e6b46bf4e6b46bf4e6b46bf4e6b46bf4e6b46bf4e6b46bf4e6b46bf4e6b46bf4e6b46bf4e6b46bf4e6b46bf4e6b46bf4 ..."
         ],
         false
      ],
      [
         "TF",
         [
            1300,
            "**************************************************************** ..."
         ],
         0,
         false,
         0,
         "2f191e9b",
         null,
         null,
         false
      ],
      [
         "TO",
         [
            1308,
            "00fe05142f191e9b053334b1053334b1053334b1053334b1053334b1053334b1053334b1053334b1053334b1053334b1053334b1053334b1053334b1053334b1 ..."
         ],
         false
      ],
      [
         "TF",
         [
            1300,
            "**************************************************************** ..."
         ],
         0,
         false,
         0,
         "25fd8a4c",
         null,
         null,
         false
      ],
      [
         "TO",
         [
            1308,
            "00fe051425fd8a4c0fd7a0660fd7a0660fd7a0660fd7a0660fd7a0660fd7a0660fd7a0660fd7a0660fd7a0660fd7a0660fd7a0660fd7a0660fd7a0660fd7a066 ..."
         ],
         false
      ],
      [
         "TF",
         [
            1300,
            "**************************************************************** ..."
         ],
         0,
         false,
         0,
         "b55e9c82",
         null,
         null,
         false
      ],
      [
         "TO",
         [
            1308,
            "00fe0514b55e9c829f74b6a89f74b6a89f74b6a89f74b6a89f74b6a89f74b6a89f74b6a89f74b6a89f74b6a89f74b6a89f74b6a89f74b6a89f74b6a89f74b6a8 ..."
         ],
         false
      ],
      [
         "TF",
         [
            1300,
            "**************************************************************** ..."
         ],
         0,
         false,
         0,
         "73e16098",
         null,
         null,
         false
      ],
      [
         "TO",
         [
            1308,
            "00fe051473e1609859cb4ab259cb4ab259cb4ab259cb4ab259cb4ab259cb4ab259cb4ab259cb4ab259cb4ab259cb4ab259cb4ab259cb4ab259cb4ab259cb4ab2 ..."
         ],
         false
      ],
      [
         "TF",
         [
            1300,
            "**************************************************************** ..."
         ],
         0,
         false,
         0,
         "5e92e146",
         null,
         null,
         false
      ],
      [
         "TO",
         [
            1308,
            "00fe05145e92e14674b8cb6c74b8cb6c74b8cb6c74b8cb6c74b8cb6c74b8cb6c74b8cb6c74b8cb6c74b8cb6c74b8cb6c74b8cb6c74b8cb6c74b8cb6c74b8cb6c ..."
         ],
         false
      ],
      [
         "TF",
         [
            1300,
            "**************************************************************** ..."
         ],
         0,
         false,
         0,
         "66841ed2",
         null,
         null,
         false
      ],
      [
         "TO",
         [
            1308,
            "00fe051466841ed24cae34f84cae34f84cae34f84cae34f84cae34f84cae34f84cae34f84cae34f84cae34f84cae34f84cae34f84cae34f84cae34f84cae34f8 ..."
         ],
         false
      ],
      [
         "TF",
         [
            1300,
            "**************************************************************** ..."
         ],
         0,
         false,
         0,
         "e6d0e1d7",
         null,
         null,
         false
      ],
      [
         "TO",
         [
            1308,
            "00fe0514e6d0e1d7ccfacbfdccfacbfdccfacbfdccfacbfdccfacbfdccfacbfdccfacbfdccfacbfdccfacbfdccfacbfdccfacbfdccfacbfdccfacbfdccfacbfd ..."
         ],
         false
      ],
      [
         "TF",
         [
            1300,
            "**************************************************************** ..."
         ],
         0,
         false,
         0,
         "48d0728e",
         null,
         null,
         false
      ],
      [
         "TO",
         [
            1308,
            "00fe051448d0728e62fa58a462fa58a462fa58a462fa58a462fa58a462fa58a462fa58a462fa58a462fa58a462fa58a462fa58a462fa58a462fa58a462fa58a4 ..."
         ],
         false
      ],
      [
         "TF",
         [
            1300,
            "**************************************************************** ..."
         ],
         0,
         false,
         0,
         "b52a56dc",
         null,
         null,
         false
      ],
      [
         "TO",
         [
            1308,
            "00fe0514b52a56dc9f007cf69f007cf69f007cf69f007cf69f007cf69f007cf69f007cf69f007cf69f007cf69f007cf69f007cf69f007cf69f007cf69f007cf6 ..."
         ],
         false
      ],
      [
         "TF",
         [
            1300,
            "**************************************************************** ..."
         ],
         0,
         false,
         0,
         "f272bbcc",
         null,
         null,
         false
      ],
      [
         "TO",
         [
            1308,
            "00fe0514f272bbccd85891e6d85891e6d85891e6d85891e6d85891e6d85891e6d85891e6d85891e6d85891e6d85891e6d85891e6d85891e6d85891e6d85891e6 ..."
         ],
         false
      ],
      [
         "TF",
         [
            1300,
            "**************************************************************** ..."
         ],
         0,
         false,
         0,
         "121ae3c7",
         null,
         null,
         false
      ],
      [
         "TO",
         [
            1308,
            "00fe0514121ae3c73830c9ed3830c9ed3830c9ed3830c9ed3830c9ed3830c9ed3830c9ed3830c9ed3830c9ed3830c9ed3830c9ed3830c9ed3830c9ed3830c9ed ..."
         ],
         false
      ],
      [
         "TF",
         [
            1300,
            "**************************************************************** ..."
         ],
         0,
         false,
         0,
         "580a95dc",
         null,
         null,
         false
      ],
      [
         "TO",
         [
            1308,
            "00fe0514580a95dc7220bff67220bff67220bff67220bff67220bff67220bff67220bff67220bff67220bff67220bff67220bff67220bff67220bff67220bff6 ..."
         ],
         false
      ],
      [
         "TF",
         [
            1300,
            "**************************************************************** ..."
         ],
         0,
         false,
         0,
         "ca28f4a7",
         null,
         null,
         false
      ],
      [
         "TO",
         [
            1308,
            "00fe0514ca28f4a7e002de8de002de8de002de8de002de8de002de8de002de8de002de8de002de8de002de8de002de8de002de8de002de8de002de8de002de8d ..."
         ],
         false
      ],
      [
         "TF",
         [
            1300,
            "**************************************************************** ..."
         ],
         0,
         false,
         0,
         "d6709f82",
         null,
         null,
         false
      ],
      [
         "TO",
         [
            1308,
            "00fe0514d6709f82fc5ab5a8fc5ab5a8fc5ab5a8fc5ab5a8fc5ab5a8fc5ab5a8fc5ab5a8fc5ab5a8fc5ab5a8fc5ab5a8fc5ab5a8fc5ab5a8fc5ab5a8fc5ab5a8 ..."
         ],
         false
      ],
      [
         "TF",
         [
            1300,
            "**************************************************************** ..."
         ],
         0,
         false,
         0,
         "182b61df",
         null,
         null,
         false
      ],
      [
         "TO",
         [
            1308,
            "00fe0514182b61df32014bf532014bf532014bf532014bf532014bf532014bf532014bf532014bf532014bf532014bf532014bf532014bf532014bf532014bf5 ..."
         ],
         false
      ],
      [
         "TF",
         [
            1300,
            "**************************************************************** ..."
         ],
         0,
         false,
         0,
         "42352085",
         null,
         null,
         false
      ],
      [
         "TO",
         [
            1308,
            "00fe051442352085681f0aaf681f0aaf681f0aaf681f0aaf681f0aaf681f0aaf681f0aaf681f0aaf681f0aaf681f0aaf681f0aaf681f0aaf681f0aaf681f0aaf ..."
         ],
         false
      ],
      [
         "TF",
         [
            1300,
            "**************************************************************** ..."
         ],
         0,
         false,
         0,
         "8f9420f2",
         null,
         null,
         false
      ],
      [
         "TO",
         [
            1308,
            "00fe05148f9420f2a5be0ad8a5be0ad8a5be0ad8a5be0ad8a5be0ad8a5be0ad8a5be0ad8a5be0ad8a5be0ad8a5be0ad8a5be0ad8a5be0ad8a5be0ad8a5be0ad8 ..."
         ],
         false
      ],
      [
         "TF",
         [
            1300,
            "**************************************************************** ..."
         ],
         0,
         false,
         0,
         "d372ae3b",
         null,
         null,
         false
      ],
      [
         "TO",
         [
            1308,
            "00fe0514d372ae3bf9588411f9588411f9588411f9588411f9588411f9588411f9588411f9588411f9588411f9588411f9588411f9588411f9588411f9588411 ..."
         ],
         false
      ],
      [
         "TF",
         [
            1300,
            "**************************************************************** ..."
         ],
         0,
         false,
         0,
         "25ab17ae",
         null,
         null,
         false
      ],
      [
         "TO",
         [
            1308,
            "00fe051425ab17ae0f813d840f813d840f813d840f813d840f813d840f813d840f813d840f813d840f813d840f813d840f813d840f813d840f813d840f813d84 ..."
         ],
         false
      ],
      [
         "TF",
         [
            1300,
            "**************************************************************** ..."
         ],
         0,
         false,
         0,
         "080653b5",
         null,
         null,
         false
      ],
      [
         "TO",
         [
            1308,
            "00fe0514080653b5222c799f222c799f222c799f222c799f222c799f222c799f222c799f222c799f222c799f222c799f222c799f222c799f222c799f222c799f ..."
         ],
         false
      ],
      [
         "TF",
         [
            1300,
            "**************************************************************** ..."
         ],
         0,
         false,
         0,
         "6769d4d8",
         null,
         null,
         false
      ],
      [
         "TO",
         [
            1308,
            "00fe05146769d4d84d43fef24d43fef24d43fef24d43fef24d43fef24d43fef24d43fef24d43fef24d43fef24d43fef24d43fef24d43fef24d43fef24d43fef2 ..."
         ],
         false
      ],
      [
         "TF",
         [
            1300,
            "**************************************************************** ..."
         ],
         0,
         false,
         0,
         "188abc81",
         null,
         null,
         false
      ],
      [
         "TO",
         [
            1308,
            "00fe0514188abc8132a096ab32a096ab32a096ab32a096ab32a096ab32a096ab32a096ab32a096ab32a096ab32a096ab32a096ab32a096ab32a096ab32a096ab ..."
         ],
         false
      ],
      [
         "TF",
         [
            1300,
            "**************************************************************** ..."
         ],
         0,
         false,
         0,
         "801fb05c",
         null,
         null,
         false
      ],
      [
         "TO",
         [
            1308,
            "00fe0514801fb05caa359a76aa359a76aa359a76aa359a76aa359a76aa359a76aa359a76aa359a76aa359a76aa359a76aa359a76aa359a76aa359a76aa359a76 ..."
         ],
         false
      ],
      [
         "TF",
         [
            1300,
            "**************************************************************** ..."
         ],
         0,
         false,
         0,
         "8141f429",
         null,
         null,
         false
      ],
      [
         "TO",
         [
            1308,
            "00fe05148141f429ab6bde03ab6bde03ab6bde03ab6bde03ab6bde03ab6bde03ab6bde03ab6bde03ab6bde03ab6bde03ab6bde03ab6bde03ab6bde03ab6bde03 ..."
         ],
         false
      ],
      [
         "TF",
         [
            1300,
            "**************************************************************** ..."
         ],
         0,
         false,
         0,
         "544478ef",
         null,
         null,
         false
      ],
      [
         "TO",
         [
            1308,
            "00fe0514544478ef7e6e52c57e6e52c57e6e52c57e6e52c57e6e52c57e6e52c57e6e52c57e6e52c57e6e52c57e6e52c57e6e52c57e6e52c57e6e52c57e6e52c5 ..."
         ],
         false
      ],
      [
         "TF",
         [
            1300,
            "**************************************************************** ..."
         ],
         0,
         false,
         0,
         "4c1078f0",
         null,
         null,
         false
      ],
      [
         "TO",
         [
            1308,
            "00fe05144c1078f0663a52da663a52da663a52da663a52da663a52da663a52da663a52da663a52da663a52da663a52da663a52da663a52da663a52da663a52da ..."
         ],
         false
      ],
      [
         "TF",
         [
            1300,
            "**************************************************************** ..."
         ],
         0,
         false,
         0,
         "a449b17e",
         null,
         null,
         false
      ],
      [
         "TO",
         [
            1308,
            "00fe0514a449b17e8e639b548e639b548e639b548e639b548e639b548e639b548e639b548e639b548e639b548e639b548e639b548e639b548e639b548e639b54 ..."
         ],
         false
      ],
      [
         "TF",
         [
            1300,
            "**************************************************************** ..."
         ],
         0,
         false,
         0,
         "a1b6ccaa",
         null,
         null,
         false
      ],
      [
         "TO",
         [
            1308,
            "00fe0514a1b6ccaa8b9ce6808b9ce6808b9ce6808b9ce6808b9ce6808b9ce6808b9ce6808b9ce6808b9ce6808b9ce6808b9ce6808b9ce6808b9ce6808b9ce680 ..."
         ],
         false
      ],
      [
         "TF",
         [
            1300,
            "**************************************************************** ..."
         ],
         0,
         false,
         0,
         "46e508b5",
         null,
         null,
         false
      ],
      [
         "TO",
         [
            1308,
            "00fe051446e508b56ccf229f6ccf229f6ccf229f6ccf229f6ccf229f6ccf229f6ccf229f6ccf229f6ccf229f6ccf229f6ccf229f6ccf229f6ccf229f6ccf229f ..."
         ],
         false
      ],
      [
         "TF",
         [
            536,
            "**************************************************************** ..."
         ],
         0,
         true,
         0,
         "7ada9d69",
         null,
         null,
         false
      ],
      [
         "TO",
         [
            544,
            "80fe02187ada9d6950f0b74350f0b74350f0b74350f0b74350f0b74350f0b74350f0b74350f0b74350f0b74350f0b74350f0b74350f0b74350f0b74350f0b743 ..."
         ],
         false
      ],
      [
         "KL",
         10
      ],
      [
         "RO",
         [
            65536,
            "817f00000000000100002a2a2a2a2a2a2a2a2a2a2a2a2a2a2a2a2a2a2a2a2a2a2a2a2a2a2a2a2a2a2a2a2a2a2a2a2a2a2a2a2a2a2a2a2a2a2a2a2a2a2a2a2a2a ..."
         ]
      ],
      [
         "RO",
         [
            10,
            "2a2a2a2a2a2a2a2a2a2a"
         ]
      ],
      [
         "RF",
         [
            65536,
            "**************************************************************** ..."
         ],
         1,
         true,
         0,
         false,
         null
      ],
      [
         "TF",
         [
            2,
            "0x03e8"
         ],
         8,
         true,
         0,
         "a3505700",
         null,
         null,
         false
      ],
      [
         "TO",
         [
            8,
            "8882a3505700a0b8"
         ],
         false
      ]
   ]
}