{
   "agent": "websock server",
   "behavior": "OK",
   "behaviorClose": "OK",
   "case": 36,
   "closedByMe": false,
   "createStats": true,
   "createWirelog": true,
   "description": "Send frame with reserved non-control <b>Opcode = 4</b> and non-empty payload.",
   "droppedByMe": false,
   "duration": 1,
   "expectation": "The connection is failed immediately.",
   "expected": {
      "OK": []
   },
   "expectedClose": {
      "closeCode": [
         1002
      ],
      "closedByMe": false,
      "requireClean": false
   },
   "failedByMe": false,
   "httpRequest": "GET /ws HTTP/1.1\r\nUser-Agent: AutobahnTestSuite/25.10.1-0.10.9\r\nHost: 127.0.0.1:8888\r\nUpgrade: WebSocket\r\nConnection: Upgrade\r\nPragma: no-cache\r\nCache-Control: no-cache\r\nSec-WebSocket-Key: I7DL3vkb709BswACNHsUTw==\r\nSec-WebSocket-Version: 13\r\n\r\n",
   "httpResponse": "HTTP/1.1 101 Switching Protocols\r\nDate: Sat, 07 Mar 2026 16:48:40 GMT\r\nUpgrade: websocket\r\nConnection: Upgrade\r\nSec-Websocket-Accept: XPPptXqKF95/Bw8zPpnxJZqR/dg=\r\n\r\n",
   "id": "4.1.2",
   "isServer": false,
   "localCloseCode": null,
   "localCloseReason": null,
   "received": [],
   "remoteCloseCode": null,
   "remoteCloseReason": null,
   "reportCompressionRatio": false,
   "reportTime": false,
   "result": "Actual events match at least one expected.",
   "resultClose": "Connection was properly closed",
   "rxFrameStats": {},
   "rxOctetStats": {
      "166": 1
   },
   "started": "2026-03-07T16:48:40.194Z",
   "trafficStats": null,
   "txFrameStats": {
      "4": 1
   },
   "txOctetStats": {
      "29": 1,
      "244": 1
   },
   "wasClean": false,
   "wasCloseHandshakeTimeout": false,
   "wasNotCleanReason": "peer dropped the TCP connection without previous WebSocket closing handshake",
   "wasOpenHandshakeTimeout": false,
   "wasServerConnectionDropTimeout": false,
   "wirelog": [
      [
         "TO",
         [
            244,
            "474554202f777320485454502f312e310d0a557365722d4167656e743a204175746f6261686e5465737453756974652f32352e31302e312d302e31302e390d0a ..."
         ],
         false
      ],
      [
         "RO",
         [
            166,
            "485454502f312e312031303120537769746368696e672050726f746f636f6c730d0a446174653a205361742c203037204d617220323032362031363a34383a34 ..."
         ]
      ],
      [
         "TF",
         [
            23,
            "reserved opcode payload"
         ],
         4,
         true,
         0,
         "c15ff71c",
         null,
         null,
         false
      ],
      [
         "TO",
         [
            29,
            "8497c15ff71cb33a8479b3299278e130877fae3b923cb13e8e70ae3e93"
         ],
         false
      ],
      [
         "KL",
         1
      ]
   ]
}