{
   "agent": "websock server",
   "behavior": "OK",
   "behaviorClose": "UNCLEAN",
   "case": 26,
   "closedByMe": true,
   "createStats": true,
   "createWirelog": true,
   "description": "Send 10 Pings with payload.",
   "droppedByMe": false,
   "duration": 3,
   "expectation": "Pongs for our Pings with all the payloads. Note: This is not required by the Spec .. but we check for this behaviour anyway. Clean close with normal code.",
   "expected": {
      "OK": [
         [
            "pong",
            "payload-0"
         ],
         [
            "pong",
            "payload-1"
         ],
         [
            "pong",
            "payload-2"
         ],
         [
            "pong",
            "payload-3"
         ],
         [
            "pong",
            "payload-4"
         ],
         [
            "pong",
            "payload-5"
         ],
         [
            "pong",
            "payload-6"
         ],
         [
            "pong",
            "payload-7"
         ],
         [
            "pong",
            "payload-8"
         ],
         [
            "pong",
            "payload-9"
         ]
      ]
   },
   "expectedClose": {
      "closeCode": [
         1000
      ],
      "closedByMe": true,
      "requireClean": true
   },
   "failedByMe": false,
   "httpRequest": "GET /ws HTTP/1.1\r\nUser-Agent: AutobahnTestSuite/25.10.1-0.10.9\r\nHost: 127.0.0.1:8888\r\nUpgrade: WebSocket\r\nConnection: Upgrade\r\nPragma: no-cache\r\nCache-Control: no-cache\r\nSec-WebSocket-Key: fDsqRsEhZQETRl19WXwkLg==\r\nSec-WebSocket-Version: 13\r\n\r\n",
   "httpResponse": "HTTP/1.1 101 Switching Protocols\r\nDate: Fri, 10 Apr 2026 13:09:33 GMT\r\nUpgrade: websocket\r\nConnection: Upgrade\r\nSec-Websocket-Accept: LQfF2GaGnCS23qmz41wUKpuHcaw=\r\n\r\n",
   "id": "2.10",
   "isServer": false,
   "localCloseCode": 1000,
   "localCloseReason": null,
   "received": [
      [
         "pong",
         "payload-0"
      ],
      [
         "pong",
         "payload-1"
      ],
      [
         "pong",
         "payload-2"
      ],
      [
         "pong",
         "payload-3"
      ],
      [
         "pong",
         "payload-4"
      ],
      [
         "pong",
         "payload-5"
      ],
      [
         "pong",
         "payload-6"
      ],
      [
         "pong",
         "payload-7"
      ],
      [
         "pong",
         "payload-8"
      ],
      [
         "pong",
         "payload-9"
      ]
   ],
   "remoteCloseCode": null,
   "remoteCloseReason": null,
   "reportCompressionRatio": false,
   "reportTime": false,
   "result": "Actual events match at least one expected.",
   "resultClose": "The spec requires the connection to be failed cleanly here",
   "rxFrameStats": {
      "10": 10
   },
   "rxOctetStats": {
      "33": 1,
      "77": 1,
      "166": 1
   },
   "started": "2026-04-10T13:09:33.587Z",
   "trafficStats": null,
   "txFrameStats": {
      "8": 1,
      "9": 10
   },
   "txOctetStats": {
      "8": 1,
      "15": 10,
      "244": 1
   },
   "wasClean": false,
   "wasCloseHandshakeTimeout": false,
   "wasNotCleanReason": "peer dropped the TCP connection without previous WebSocket closing handshake",
   "wasOpenHandshakeTimeout": false,
   "wasServerConnectionDropTimeout": false,
   "wirelog": [
      [
         "TO",
         [
            244,
            "474554202f777320485454502f312e310d0a557365722d4167656e743a204175746f6261686e5465737453756974652f32352e31302e312d302e31302e390d0a ..."
         ],
         false
      ],
      [
         "RO",
         [
            166,
            "485454502f312e312031303120537769746368696e672050726f746f636f6c730d0a446174653a204672692c2031302041707220323032362031333a30393a33 ..."
         ]
      ],
      [
         "TF",
         [
            9,
            "payload-0"
         ],
         9,
         true,
         0,
         "0ca1a26f",
         null,
         null,
         false
      ],
      [
         "TO",
         [
            15,
            "89890ca1a26f7cc0db0363c0c6423c"
         ],
         false
      ],
      [
         "TF",
         [
            9,
            "payload-1"
         ],
         9,
         true,
         0,
         "c1f0915b",
         null,
         null,
         false
      ],
      [
         "TO",
         [
            15,
            "8989c1f0915bb191e837ae91f576f0"
         ],
         false
      ],
      [
         "TF",
         [
            9,
            "payload-2"
         ],
         9,
         true,
         0,
         "97c4f5b7",
         null,
         null,
         false
      ],
      [
         "TO",
         [
            15,
            "898997c4f5b7e7a58cdbf8a5919aa5"
         ],
         false
      ],
      [
         "TF",
         [
            9,
            "payload-3"
         ],
         9,
         true,
         0,
         "7aae8bb0",
         null,
         null,
         false
      ],
      [
         "TO",
         [
            15,
            "89897aae8bb00acff2dc15cfef9d49"
         ],
         false
      ],
      [
         "TF",
         [
            9,
            "payload-4"
         ],
         9,
         true,
         0,
         "f5ac82b5",
         null,
         null,
         false
      ],
      [
         "TO",
         [
            15,
            "8989f5ac82b585cdfbd99acde698c1"
         ],
         false
      ],
      [
         "TF",
         [
            9,
            "payload-5"
         ],
         9,
         true,
         0,
         "33219f19",
         null,
         null,
         false
      ],
      [
         "TO",
         [
            15,
            "898933219f194340e6755c40fb3406"
         ],
         false
      ],
      [
         "TF",
         [
            9,
            "payload-6"
         ],
         9,
         true,
         0,
         "27545a18",
         null,
         null,
         false
      ],
      [
         "TO",
         [
            15,
            "898927545a185735237448353e3511"
         ],
         false
      ],
      [
         "TF",
         [
            9,
            "payload-7"
         ],
         9,
         true,
         0,
         "f7cad2fa",
         null,
         null,
         false
      ],
      [
         "TO",
         [
            15,
            "8989f7cad2fa87abab9698abb6d7c0"
         ],
         false
      ],
      [
         "TF",
         [
            9,
            "payload-8"
         ],
         9,
         true,
         0,
         "f15d39f2",
         null,
         null,
         false
      ],
      [
         "TO",
         [
            15,
            "8989f15d39f2813c409e9e3c5ddfc9"
         ],
         false
      ],
      [
         "TF",
         [
            9,
            "payload-9"
         ],
         9,
         true,
         0,
         "deda4ac7",
         null,
         null,
         false
      ],
      [
         "TO",
         [
            15,
            "8989deda4ac7aebb33abb1bb2eeae7"
         ],
         false
      ],
      [
         "TI",
         3
      ],
      [
         "RO",
         [
            33,
            "8a097061796c6f61642d308a097061796c6f61642d318a097061796c6f61642d32"
         ]
      ],
      [
         "RF",
         [
            9,
            "payload-0"
         ],
         10,
         true,
         0,
         false,
         null
      ],
      [
         "RF",
         [
            9,
            "payload-1"
         ],
         10,
         true,
         0,
         false,
         null
      ],
      [
         "RF",
         [
            9,
            "payload-2"
         ],
         10,
         true,
         0,
         false,
         null
      ],
      [
         "RO",
         [
            77,
            "8a097061796c6f61642d338a097061796c6f61642d348a097061796c6f61642d358a097061796c6f61642d368a097061796c6f61642d378a097061796c6f6164 ..."
         ]
      ],
      [
         "RF",
         [
            9,
            "payload-3"
         ],
         10,
         true,
         0,
         false,
         null
      ],
      [
         "RF",
         [
            9,
            "payload-4"
         ],
         10,
         true,
         0,
         false,
         null
      ],
      [
         "RF",
         [
            9,
            "payload-5"
         ],
         10,
         true,
         0,
         false,
         null
      ],
      [
         "RF",
         [
            9,
            "payload-6"
         ],
         10,
         true,
         0,
         false,
         null
      ],
      [
         "RF",
         [
            9,
            "payload-7"
         ],
         10,
         true,
         0,
         false,
         null
      ],
      [
         "RF",
         [
            9,
            "payload-8"
         ],
         10,
         true,
         0,
         false,
         null
      ],
      [
         "RF",
         [
            9,
            "payload-9"
         ],
         10,
         true,
         0,
         false,
         null
      ],
      [
         "TF",
         [
            2,
            "0x03e8"
         ],
         8,
         true,
         0,
         "51032d59",
         null,
         null,
         false
      ],
      [
         "TO",
         [
            8,
            "888251032d5952eb"
         ],
         false
      ]
   ]
}