{
   "agent": "websock server",
   "behavior": "FAILED",
   "behaviorClose": "FAILED",
   "case": 316,
   "closedByMe": false,
   "createStats": true,
   "createWirelog": false,
   "description": "Send 1000 compressed messages each of payload size 131072, auto-fragment to 256 octets. Use default permessage-deflate offer.",
   "droppedByMe": false,
   "duration": 749,
   "expectation": "Receive echo'ed messages (with payload as sent). Timeout case after 480 secs.",
   "expected": {},
   "expectedClose": {
      "closeCode": [
         1000
      ],
      "closedByMe": true,
      "requireClean": true
   },
   "failedByMe": false,
   "httpRequest": "GET /ws HTTP/1.1\r\nUser-Agent: AutobahnTestSuite/25.10.1-0.10.9\r\nHost: 127.0.0.1:8888\r\nUpgrade: WebSocket\r\nConnection: Upgrade\r\nPragma: no-cache\r\nCache-Control: no-cache\r\nSec-WebSocket-Key: U62q/tBZrGHWtKGThFnSog==\r\nSec-WebSocket-Extensions: permessage-deflate; client_no_context_takeover; client_max_window_bits\r\nSec-WebSocket-Version: 13\r\n\r\n",
   "httpResponse": "HTTP/1.1 101 Switching Protocols\r\nDate: Wed, 12 Nov 2025 13:23:29 GMT\r\nSec-Websocket-Extensions: permessage-deflate; client_no_context_takeover\r\nUpgrade: websocket\r\nConnection: Upgrade\r\nSec-Websocket-Accept: kNTFMXBQUqY8h2alpCfZRLxaQyw=\r\n\r\n",
   "id": "12.1.15",
   "isServer": false,
   "localCloseCode": null,
   "localCloseReason": null,
   "received": [],
   "remoteCloseCode": null,
   "remoteCloseReason": null,
   "reportCompressionRatio": true,
   "reportTime": true,
   "result": "Case did not finish within 480 seconds.",
   "resultClose": "The connection was failed by the wrong endpoint",
   "rxFrameStats": {
      "1": 161
   },
   "rxOctetStats": {
      "240": 1,
      "5576": 1,
      "5579": 1,
      "5581": 1,
      "5582": 2,
      "5586": 1,
      "5587": 1,
      "5588": 2,
      "5590": 1,
      "5591": 1,
      "5592": 1,
      "5593": 1,
      "5594": 1,
      "5595": 1,
      "5599": 4,
      "5600": 2,
      "5601": 1,
      "5602": 1,
      "5603": 1,
      "5604": 1,
      "5605": 3,
      "5606": 3,
      "5607": 3,
      "5608": 3,
      "5609": 1,
      "5611": 1,
      "5614": 1,
      "5616": 2,
      "5617": 1,
      "5619": 1,
      "5624": 1,
      "5625": 1,
      "5630": 1,
      "5640": 1,
      "5643": 1,
      "5647": 1,
      "5648": 2,
      "5665": 1,
      "5667": 1,
      "5671": 1,
      "5673": 1,
      "5678": 2,
      "5679": 1,
      "5681": 3,
      "5682": 1,
      "5683": 2,
      "5684": 3,
      "5685": 3,
      "5686": 2,
      "5687": 4,
      "5688": 4,
      "5689": 1,
      "5690": 5,
      "5691": 1,
      "5692": 5,
      "5693": 4,
      "5694": 3,
      "5696": 5,
      "5697": 4,
      "5698": 4,
      "5699": 2,
      "5700": 3,
      "5701": 4,
      "5702": 3,
      "5704": 6,
      "5705": 2,
      "5706": 2,
      "5707": 1,
      "5708": 3,
      "5709": 1,
      "5710": 3,
      "5711": 3,
      "5713": 2,
      "5718": 1,
      "5720": 1,
      "5722": 2,
      "5723": 1,
      "5724": 2,
      "5726": 2,
      "5727": 1,
      "5728": 1,
      "5729": 1,
      "5751": 1
   },
   "started": "2025-11-12T13:23:29.766Z",
   "trafficStats": null,
   "txFrameStats": {
      "0": 3564,
      "1": 162
   },
   "txOctetStats": {
      "70": 1,
      "72": 1,
      "73": 1,
      "75": 1,
      "78": 1,
      "79": 3,
      "80": 1,
      "81": 1,
      "82": 2,
      "84": 2,
      "85": 1,
      "86": 3,
      "87": 2,
      "88": 2,
      "89": 1,
      "92": 1,
      "96": 1,
      "99": 2,
      "102": 1,
      "103": 2,
      "104": 1,
      "105": 2,
      "106": 1,
      "112": 1,
      "113": 1,
      "114": 2,
      "116": 1,
      "117": 2,
      "120": 1,
      "126": 1,
      "127": 1,
      "128": 1,
      "129": 1,
      "131": 1,
      "136": 1,
      "137": 1,
      "138": 2,
      "146": 1,
      "158": 1,
      "166": 1,
      "167": 1,
      "170": 1,
      "172": 2,
      "173": 1,
      "174": 1,
      "175": 4,
      "176": 1,
      "180": 2,
      "181": 2,
      "182": 2,
      "184": 1,
      "186": 1,
      "187": 4,
      "188": 2,
      "189": 2,
      "190": 3,
      "192": 3,
      "193": 2,
      "194": 2,
      "195": 5,
      "196": 1,
      "197": 1,
      "199": 3,
      "200": 1,
      "202": 1,
      "203": 2,
      "204": 2,
      "205": 4,
      "208": 5,
      "209": 3,
      "210": 1,
      "211": 3,
      "213": 1,
      "214": 6,
      "215": 2,
      "216": 3,
      "217": 3,
      "218": 1,
      "219": 1,
      "220": 1,
      "221": 4,
      "222": 4,
      "223": 2,
      "224": 2,
      "225": 1,
      "226": 1,
      "227": 1,
      "228": 1,
      "230": 1,
      "232": 1,
      "235": 1,
      "243": 1,
      "253": 1,
      "264": 3564,
      "342": 1
   },
   "wasClean": false,
   "wasCloseHandshakeTimeout": false,
   "wasNotCleanReason": "peer dropped the TCP connection without previous WebSocket closing handshake",
   "wasOpenHandshakeTimeout": false,
   "wasServerConnectionDropTimeout": false,
   "wirelog": [
      [
         "TO",
         [
            342,
            "474554202f777320485454502f312e310d0a557365722d4167656e743a204175746f6261686e5465737453756974652f32352e31302e312d302e31302e390d0a ..."
         ],
         false
      ],
      [
         "RO",
         [
            240,
            "485454502f312e312031303120537769746368696e672050726f746f636f6c730d0a446174653a205765642c203132204e6f7620323032352031333a32333a32 ..."
         ]
      ],
      [
         "WLM",
         false
      ],
      [
         "TI",
         480
      ]
   ]
}